azure_iot_edge_runtime_ctl-1.0.0rc24.dist-info/DESCRIPTION.rst
azure_iot_edge_runtime_ctl-1.0.0rc24.dist-info/METADATA
azure_iot_edge_runtime_ctl-1.0.0rc24.dist-info/RECORD
azure_iot_edge_runtime_ctl-1.0.0rc24.dist-info/WHEEL
azure_iot_edge_runtime_ctl-1.0.0rc24.dist-info/entry_points.txt
azure_iot_edge_runtime_ctl-1.0.0rc24.dist-info/metadata.json
azure_iot_edge_runtime_ctl-1.0.0rc24.dist-info/top_level.txt
edgectl/__init__.py
edgectl/errors.py
edgectl/cli/__init__.py
edgectl/cli/edgecli.py
edgectl/config/__init__.py
edgectl/config/azure-iot-edge-config-reference.json
edgectl/config/certconfig.py
edgectl/config/configbase.py
edgectl/config/default.py
edgectl/config/dockerconfig.py
edgectl/config/edgeconfig.py
edgectl/config/edgeconstants.py
edgectl/deployment/__init__.py
edgectl/deployment/commandbase.py
edgectl/deployment/commandfactory.py
edgectl/deployment/deploymentdocker.py
edgectl/host/__init__.py
edgectl/host/dockerclient.py
edgectl/host/edgehostplatform.py
edgectl/parser/__init__.py
edgectl/parser/edgeconfigparser.py
edgectl/parser/edgeconfigparsercli.py
edgectl/parser/edgeconfigparserfactory.py
edgectl/parser/edgeconfigparserfile.py
edgectl/test/__init__.py
edgectl/test/config/__init__.py
edgectl/test/config/test_cert_config_unit.py
edgectl/test/config/test_default.py
edgectl/test/config/test_default_unit.py
edgectl/test/config/test_dockerconfig_unit.py
edgectl/test/config/test_edgeconfig_unit.py
edgectl/test/deployment/__init__.py
edgectl/test/deployment/test_deployment_unit.py
edgectl/test/host/__init__.py
edgectl/test/host/test_dockerclient.py
edgectl/test/host/test_dockerclient_int.py
edgectl/test/utils/__init__.py
edgectl/test/utils/test_certutil_unit.py
edgectl/test/utils/test_edgeutils.py
edgectl/utils/__init__.py
edgectl/utils/certutil.py
edgectl/utils/edgeutils.py
