Metadata-Version: 2.0
Name: azure-iot-edge-runtime-ctl
Version: 1.0.0rc24
Summary: Azure IoT Edge Runtime Control
Home-page: https://github.com/azure/iot-edge
Author: Azure IoT Edge
Author-email: edgedevs@microsoft.com
License: MIT
Keywords: azure iot edge
Platform: UNKNOWN
Classifier: Intended Audience :: Developers
Classifier: License :: OSI Approved :: MIT License
Classifier: Programming Language :: Python :: 2
Classifier: Programming Language :: Python :: 2.7
Classifier: Programming Language :: Python :: 3
Provides-Extra: test
Provides-Extra: dev
Requires-Dist: docker[tls] (~=3.1)
Requires-Dist: enum34
Requires-Dist: pyOpenSSL
Requires-Dist: pypiwin32 (<222); sys_platform == "win32"
Provides-Extra: dev
Requires-Dist: check-manifest; extra == 'dev'
Provides-Extra: test
Requires-Dist: coverage; extra == 'test'
Requires-Dist: mock; extra == 'test'
